[
  {
    "slug": "chto-takoe-rag-i-kak-on-pomogaet-neirosetyam-rabotat-s-vashimi-dannymi",
    "title": "Что такое RAG и как он помогает нейросетям работать с вашими данными",
    "description": "Разбираем, что такое RAG...",
    "date": "2025-08-11",
    "cover": "/assets/posts/RAG.png",
    "md": "posts/RAG.md",
    "category": "useful"
  },
  {
    "slug": "kak-nejroseti-menyayut-podhod-k-avtomatizacii-biznes-processov",
    "title": "Как нейросети меняют подход к автоматизации бизнес-процессов",
    "description": "Как ИИ перестраивает автоматизацию...",
    "date": "2025-08-12",
    "cover": "/assets/posts/article2.png",
    "md": "posts/auto.md",
    "category": "business-cases"
  }
]
